safeurl/__init__.py
safeurl/safeurl.py
safeurl/safeurl_tests.py
SafeURL_Python-1.3.dist-info/LICENSE
SafeURL_Python-1.3.dist-info/METADATA
SafeURL_Python-1.3.dist-info/WHEEL
SafeURL_Python-1.3.dist-info/top_level.txt
SafeURL_Python-1.3.dist-info/RECORD
