Metadata-Version: 2.1
Name: SafeURL-Python
Version: 1.3
Summary: SafeURL is a library that aids developers in protecting against a class of vulnerabilities known as Server Side Request Forgery.
Project-URL: Homepage, https://github.com/IncludeSecurity/safeurl-python
License-File: LICENSE
Requires-Dist: netaddr
Requires-Dist: pycurl
